fd_magnet_link.py
fd_magnet_link-0.1.7.dist-info/entry_points.txt
fd_magnet_link-0.1.7.dist-info/METADATA
fd_magnet_link-0.1.7.dist-info/WHEEL
fd_magnet_link-0.1.7.dist-info/RECORD
