Metadata-Version: 2.1
Name: fd_magnet_link
Version: 0.1.7
Summary: 
Author: Alexstrasza03
Author-email: 77481463+Alexstrasza03@users.noreply.github.com
Requires-Python: >=3.9,<4.0
Classifier: Programming Language :: Python :: 3
Classifier: Programming Language :: Python :: 3.9
Classifier: Programming Language :: Python :: 3.10
Classifier: Programming Language :: Python :: 3.11
Classifier: Programming Language :: Python :: 3.12
